cortellis_mcp/__init__.py
cortellis_mcp/__main__.py
cortellis_mcp-0.1.0.dist-info/METADATA
cortellis_mcp-0.1.0.dist-info/WHEEL
cortellis_mcp-0.1.0.dist-info/licenses/LICENSE
cortellis_mcp-0.1.0.dist-info/RECORD
