Metadata-Version: 2.4
Name: cortellis-mcp
Version: 0.1.0
Summary: Cortellis MCP Server for drug search and ontology exploration
Project-URL: Homepage, https://github.com/uh-joan/mcp-cortellis
Project-URL: Repository, https://github.com/uh-joan/mcp-cortellis.git
Project-URL: Bug Tracker, https://github.com/uh-joan/mcp-cortellis/issues
Project-URL: Documentation, https://github.com/uh-joan/mcp-cortellis/tree/main/docs
Author-email: Joan <janisaez@gmail.com>
License: MIT License
License-File: LICENSE
Keywords: cortellis,drug-search,mcp,ontology,pharmaceutical
Classifier: Development Status :: 4 - Beta
Classifier: Environment :: Console
Classifier: Intended Audience :: Healthcare Industry
Classifier: Intended Audience :: Science/Research
Classifier: License :: OSI Approved :: MIT License
Classifier: Natural Language :: English
Classifier: Operating System :: OS Independent
Classifier: Programming Language :: Python :: 3
Classifier: Programming Language :: Python :: 3.10
Classifier: Programming Language :: Python :: 3.11
Classifier: Programming Language :: Python :: 3.12
Classifier: Topic :: Scientific/Engineering :: Bio-Informatics
Classifier: Topic :: Scientific/Engineering :: Medical Science Apps.
Requires-Python: >=3.10
Requires-Dist: mcp>=0.1.0
Requires-Dist: python-dotenv>=1.0.0
Requires-Dist: requests>=2.31.0
